README.md
setup.py
cwlgen/__init__.py
cwlgen/commandlinebinding.py
cwlgen/commandlinetool.py
cwlgen/common.py
cwlgen/import_cwl.py
cwlgen/requirements.py
cwlgen/utils.py
cwlgen/version.py
cwlgen/workflow.py
illusional.cwlgen.egg-info/PKG-INFO
illusional.cwlgen.egg-info/SOURCES.txt
illusional.cwlgen.egg-info/dependency_links.txt
illusional.cwlgen.egg-info/requires.txt
illusional.cwlgen.egg-info/top_level.txt
test/test_export.py
test/test_unit_cwlgen.py
test/test_unit_import.py
test/test_unit_requirements.py
test/test_unit_typing.py
test/test_unit_workflow.py